bashrange/__init__.py
bashrange/__main__.py
bashrange/test.py
bashrange/__pycache__/__init__.cpython-311.pyc
bashrange/__pycache__/__init__.cpython-39.pyc
bashrange/__pycache__/__main__.cpython-311.pyc
bashrange/__pycache__/__main__.cpython-39.pyc
bashrange/__pycache__/test.cpython-311.pyc
bashrange/__pycache__/test.cpython-39.pyc
bashrange-0.0.4.dist-info/LICENSE
bashrange-0.0.4.dist-info/METADATA
bashrange-0.0.4.dist-info/WHEEL
bashrange-0.0.4.dist-info/top_level.txt
bashrange-0.0.4.dist-info/RECORD
