Metadata-Version: 2.1
Name: bashrange
Version: 0.0.4
Summary: Bash range expression evaluator for your cli application
Home-page: https://github.com/mugiseyebrows/bash-range
Author: Stanislav Doronin
Author-email: mugisbrows@gmail.com
License-File: LICENSE
